.gitignore
COPYING.txt
MANIFEST.in
README.txt
setup.py
docs/CHANGES.txt
docs/CONTRIBUTORS.txt
src/collective/__init__.py
src/collective.anonfeedback.egg-info/PKG-INFO
src/collective.anonfeedback.egg-info/SOURCES.txt
src/collective.anonfeedback.egg-info/dependency_links.txt
src/collective.anonfeedback.egg-info/entry_points.txt
src/collective.anonfeedback.egg-info/namespace_packages.txt
src/collective.anonfeedback.egg-info/not-zip-safe
src/collective.anonfeedback.egg-info/requires.txt
src/collective.anonfeedback.egg-info/top_level.txt
src/collective/anonfeedback/__init__.py
src/collective/anonfeedback/configure.zcml
src/collective/anonfeedback/testing.py
src/collective/anonfeedback/browser/__init__.py
src/collective/anonfeedback/browser/configure.zcml
src/collective/anonfeedback/browser/feedback.pt
src/collective/anonfeedback/browser/feedback.py
src/collective/anonfeedback/browser/feedback_form.pt
src/collective/anonfeedback/profiles/default/actions.xml
src/collective/anonfeedback/profiles/default/metadata.xml
src/collective/anonfeedback/profiles/default/rolemap.xml
src/collective/anonfeedback/tests/__init__.py
src/collective/anonfeedback/tests/test_installed.py
src/collective/anonfeedback/tests/test_views.py