Metadata-Version: 1.1
Name: collective.anonfeedback
Version: 1.0
Summary: An anonymous feedback form
Home-page: https://github.com/collective/collective.anonfeedback
Author: Lennart Regebro
Author-email: regebro@gmail.com
License: MIT
Keywords: plone
Platform: UNKNOWN
Classifier: Framework :: Plone
Classifier: Framework :: Plone :: 4.3
Classifier: Programming Language :: Python
Classifier: Programming Language :: Python :: 2.7
